PyMemAPI/__init__.py
PyMemAPI/exception/__init__.py
PyMemAPI/exception/exception.py
PyMemAPI/PyMemAPI.py
PyMemAPI/schema/__init__.py
PyMemAPI/schema/schema.py
PyMemAPI/text2speech/__init__.py
PyMemAPI/text2speech/text2speech.py
pymemapi-0.1.0rc0.dist-info/LICENSE
pymemapi-0.1.0rc0.dist-info/WHEEL
pymemapi-0.1.0rc0.dist-info/METADATA
pymemapi-0.1.0rc0.dist-info/RECORD
