Metadata-Version: 2.1
Name: pymemapi
Version: 0.1.0rc0
Summary: Memrise API
Home-page: https://github.com/josephquang97/memrise
Author: Joseph Quang
Author-email: tquangsdh20@fsob.win
Requires-Python: >=3.6,<4.0
Classifier: Development Status :: 5 - Production/Stable
Classifier: Intended Audience :: Education
Classifier: Intended Audience :: End Users/Desktop
Classifier: License :: OSI Approved :: Apache Software License
Classifier: Operating System :: OS Independent
Classifier: Programming Language :: Python :: 3
Classifier: Programming Language :: Python :: 3.10
Classifier: Programming Language :: Python :: 3.6
Classifier: Programming Language :: Python :: 3.7
Classifier: Programming Language :: Python :: 3.8
Classifier: Programming Language :: Python :: 3.9
Requires-Dist: bs4 (>=0.0,<0.1)
Requires-Dist: googletrans (==4.0.0rc1)
Requires-Dist: memrise (>=1.3.0,<2.0.0)
Requires-Dist: pandas (>=1.3.5,<2.0.0)
Requires-Dist: pydantic (>=1.9.0,<2.0.0)
Requires-Dist: pyttsx3 (>=2.90,<3.0)
Requires-Dist: text2ipa (>=1.3,<2.0)
Project-URL: Repository, https://github.com/josephquang97/memrise
